CHANGES.rst
CONTRIBUTORS.rst
DEVELOPMENT.rst
LICENSE
MANIFEST.in
README.rst
setup.cfg
setup.py
src/unoserver/__init__.py
src/unoserver/converter.py
src/unoserver/server.py
src/unoserver_fork.egg-info/PKG-INFO
src/unoserver_fork.egg-info/SOURCES.txt
src/unoserver_fork.egg-info/dependency_links.txt
src/unoserver_fork.egg-info/entry_points.txt
src/unoserver_fork.egg-info/not-zip-safe
src/unoserver_fork.egg-info/requires.txt
src/unoserver_fork.egg-info/top_level.txt
tests/__init__.py
tests/conftest.py
tests/test_converter.py
tests/test_integration.py
tests/test_server.py
tests/documents/simple.odt
tests/documents/simple.xlsx