Metadata-Version: 2.1
Name: unoserver-fork
Version: 1.3.1
Summary: A server for file conversions with Libre Office. With function to update index
Home-page: https://github.com/AlePini/unoserver
Author: Alessandro Filippini
Author-email: ale@alepini.com
License: MIT
Keywords: libreoffice,conversion,documents,uno,unoconv
Classifier: Development Status :: 5 - Production/Stable
Classifier: Topic :: Office/Business
Classifier: Operating System :: POSIX :: Linux
Classifier: Programming Language :: Python :: 3
Classifier: Programming Language :: Python :: 3 :: Only
Classifier: Programming Language :: Python :: 3.7
Classifier: Programming Language :: Python :: 3.8
Classifier: Programming Language :: Python :: 3.9
Classifier: License :: OSI Approved :: MIT License
Requires-Python: >=3.7
Provides-Extra: devenv
License-File: LICENSE
